MANIFEST.in
README.md
requirements.txt
setup.cfg
setup.py
versioneer.py
botcity/plugins/googlesheets/__init__.py
botcity/plugins/googlesheets/_version.py
botcity/plugins/googlesheets/plugin.py
botcity/plugins/googlesheets/tests/__init__.py
botcity/plugins/googlesheets/tests/test_import.py
botcity/plugins/googlesheets/tests/test_plugin.py
botcity_googlesheets_plugin.egg-info/PKG-INFO
botcity_googlesheets_plugin.egg-info/SOURCES.txt
botcity_googlesheets_plugin.egg-info/dependency_links.txt
botcity_googlesheets_plugin.egg-info/requires.txt
botcity_googlesheets_plugin.egg-info/top_level.txt