Metadata-Version: 2.1
Name: botcity-googlesheets-plugin
Version: 0.3.0
Home-page: https://bitbucket.org/botcitydev/bot-googlesheets-plugin-python.git
Requires-Python: >=3.7
